fuckreplitdb/__init__.py
fuckreplitdb/datatest.py
fuckreplitdb-1.9.2.dist-info/licenses/LICENSE
fuckreplitdb-1.9.2.dist-info/METADATA
fuckreplitdb-1.9.2.dist-info/WHEEL
fuckreplitdb-1.9.2.dist-info/top_level.txt
fuckreplitdb-1.9.2.dist-info/RECORD
