Metadata-Version: 2.4
Name: fuckreplitdb
Version: 1.9.2
Summary: For the devs who wrote apps a bit too big with Replit DB.
Author-email: theroyalwhale <admin@dyntech.cc>
License-Expression: MIT
Classifier: Programming Language :: Python :: 3
Classifier: Operating System :: OS Independent
Requires-Python: >=3.8
License-File: LICENSE
Dynamic: license-file
